{
  "userId": "6868868beadad6994692f9ae",
  "dataType": "combined_investment_summary",
  "timestamp": "2025-07-05T18:51:33.630Z",
  "rawData": {
    "total_holdings": 30,
    "total_accounts": 2,
    "total_securities": 33,
    "institutions_count": 1,
    "combined_data": {
      "holdings": [
        {
          "account_id": "9rggQzXgqgSMZjP6VMReUVXpv3k3AoUKrkeLA",
          "cost_basis": null,
          "institution_price": 11.45,
          "institution_price_as_of": "2025-07-03",
          "institution_price_datetime": null,
          "institution_value": 0,
          "iso_currency_code": "USD",
          "quantity": 0,
          "security_id": "JmN0JX0q5EcJzZakgAaXHYzMgoMr6psQ6ZPKo",
          "unofficial_currency_code": null,
          "vested_quantity": null,
          "vested_value": null,
          "institution_name": "Merrill",
          "institution_id": "ins_115610"
        },
        {
          "account_id": "9rggQzXgqgSMZjP6VMReUVXpv3k3AoUKrkeLA",
          "cost_basis": null,
          "institution_price": 3.68,
          "institution_price_as_of": "2025-07-03",
          "institution_price_datetime": null,
          "institution_value": 0,
          "iso_currency_code": "USD",
          "quantity": 0,
          "security_id": "RqmZJoZ0w1coO7PmydbwIMzaB8agQZfdbEaXO",
          "unofficial_currency_code": null,
          "vested_quantity": null,
          "vested_value": null,
          "institution_name": "Merrill",
          "institution_id": "ins_115610"
        },
        {
          "account_id": "9rggQzXgqgSMZjP6VMReUVXpv3k3AoUKrkeLA",
          "cost_basis": null,
          "institution_price": 0.85,
          "institution_price_as_of": "2025-07-03",
          "institution_price_datetime": null,
          "institution_value": 0,
          "iso_currency_code": "USD",
          "quantity": 0,
          "security_id": "rJ6M41My0wFLwNOZykgDt3exyOxkp7fAY6n75",
          "unofficial_currency_code": null,
          "vested_quantity": null,
          "vested_value": null,
          "institution_name": "Merrill",
          "institution_id": "ins_115610"
        },
        {
          "account_id": "9rggQzXgqgSMZjP6VMReUVXpv3k3AoUKrkeLA",
          "cost_basis": null,
          "institution_price": 0.05,
          "institution_price_as_of": "2025-07-03",
          "institution_price_datetime": null,
          "institution_value": 0,
          "iso_currency_code": "USD",
          "quantity": 0,
          "security_id": "moPE4dE1yMH5xRJ8Z48YtvbZ1LZ7NVH4RwKaj",
          "unofficial_currency_code": null,
          "vested_quantity": null,
          "vested_value": null,
          "institution_name": "Merrill",
          "institution_id": "ins_115610"
        },
        {
          "account_id": "9rggQzXgqgSMZjP6VMReUVXpv3k3AoUKrkeLA",
          "cost_basis": -823.5,
          "institution_price": 0.05,
          "institution_price_as_of": "2025-07-03",
          "institution_price_datetime": null,
          "institution_value": 0.5,
          "iso_currency_code": "USD",
          "quantity": 10,
          "security_id": "XARE85EJqKsLrXzjxokRiPABJMBv8NfP8JQAM",
          "unofficial_currency_code": null,
          "vested_quantity": null,
          "vested_value": null,
          "institution_name": "Merrill",
          "institution_id": "ins_115610"
        },
        {
          "account_id": "9rggQzXgqgSMZjP6VMReUVXpv3k3AoUKrkeLA",
          "cost_basis": -1052.7,
          "institution_price": 1.1,
          "institution_price_as_of": "2025-07-03",
          "institution_price_datetime": null,
          "institution_value": 2.2,
          "iso_currency_code": "USD",
          "quantity": 2,
          "security_id": "1vAj1Eja5BIRmXqJAv6NFBJ0q30AYZfq0O6Q8",
          "unofficial_currency_code": null,
          "vested_quantity": null,
          "vested_value": null,
          "institution_name": "Merrill",
          "institution_id": "ins_115610"
        },
        {
          "account_id": "9rggQzXgqgSMZjP6VMReUVXpv3k3AoUKrkeLA",
          "cost_basis": -3160.5,
          "institution_price": 0.1,
          "institution_price_as_of": "2025-07-03",
          "institution_price_datetime": null,
          "institution_value": 3,
          "iso_currency_code": "USD",
          "quantity": 30,
          "security_id": "7dD8KV8owvUX4XDnJVyeHLPy8Kyr9dFzwx7ep",
          "unofficial_currency_code": null,
          "vested_quantity": null,
          "vested_value": null,
          "institution_name": "Merrill",
          "institution_id": "ins_115610"
        },
        {
          "account_id": "9rggQzXgqgSMZjP6VMReUVXpv3k3AoUKrkeLA",
          "cost_basis": -815.35,
          "institution_price": 3.6,
          "institution_price_as_of": "2025-07-03",
          "institution_price_datetime": null,
          "institution_value": 3.6,
          "iso_currency_code": "USD",
          "quantity": 1,
          "security_id": "96d5AO5gLjCoqaeEex91UB1YdrYymNfrVZwxA",
          "unofficial_currency_code": null,
          "vested_quantity": null,
          "vested_value": null,
          "institution_name": "Merrill",
          "institution_id": "ins_115610"
        },
        {
          "account_id": "9rggQzXgqgSMZjP6VMReUVXpv3k3AoUKrkeLA",
          "cost_basis": -1360.5,
          "institution_price": 0.14,
          "institution_price_as_of": "2025-07-03",
          "institution_price_datetime": null,
          "institution_value": 4.2,
          "iso_currency_code": "USD",
          "quantity": 30,
          "security_id": "XARE85EJqKsLoVnPjM1McPABJMBv8NfPMDKkx",
          "unofficial_currency_code": null,
          "vested_quantity": null,
          "vested_value": null,
          "institution_name": "Merrill",
          "institution_id": "ins_115610"
        },
        {
          "account_id": "VjaaRvpa8acogEkLmoX1CpvRVm9mbOfLaX1de",
          "cost_basis": null,
          "institution_price": 1,
          "institution_price_as_of": "2025-07-03",
          "institution_price_datetime": null,
          "institution_value": 6,
          "iso_currency_code": "USD",
          "quantity": 6,
          "security_id": "EvByboy6Z7I4zm1p1Ya1TQ5R4YRjPMfZErRde",
          "unofficial_currency_code": null,
          "vested_quantity": null,
          "vested_value": null,
          "institution_name": "Merrill",
          "institution_id": "ins_115610"
        },
        {
          "account_id": "9rggQzXgqgSMZjP6VMReUVXpv3k3AoUKrkeLA",
          "cost_basis": -1153.5,
          "institution_price": 1.42,
          "institution_price_as_of": "2025-07-03",
          "institution_price_datetime": null,
          "institution_value": 14.2,
          "iso_currency_code": "USD",
          "quantity": 10,
          "security_id": "pJPM4LMBNQFwPmy0jJePt8ZPB4P5yAfQ7D69w",
          "unofficial_currency_code": null,
          "vested_quantity": null,
          "vested_value": null,
          "institution_name": "Merrill",
          "institution_id": "ins_115610"
        },
        {
          "account_id": "9rggQzXgqgSMZjP6VMReUVXpv3k3AoUKrkeLA",
          "cost_basis": -2800.5,
          "institution_price": 0.61,
          "institution_price_as_of": "2025-07-03",
          "institution_price_datetime": null,
          "institution_value": 18.3,
          "iso_currency_code": "USD",
          "quantity": 30,
          "security_id": "yPmM6kMrNBHBkQZY58XkIXxEeYEb0KCDpaPgQ",
          "unofficial_currency_code": null,
          "vested_quantity": null,
          "vested_value": null,
          "institution_name": "Merrill",
          "institution_id": "ins_115610"
        },
        {
          "account_id": "9rggQzXgqgSMZjP6VMReUVXpv3k3AoUKrkeLA",
          "cost_basis": -2529.4,
          "institution_price": 6.8,
          "institution_price_as_of": "2025-07-03",
          "institution_price_datetime": null,
          "institution_value": 27.2,
          "iso_currency_code": "USD",
          "quantity": 4,
          "security_id": "96d5AO5gLjCoqrDdx948IB1YdrYymNfrVLoRR",
          "unofficial_currency_code": null,
          "vested_quantity": null,
          "vested_value": null,
          "institution_name": "Merrill",
          "institution_id": "ins_115610"
        },
        {
          "account_id": "9rggQzXgqgSMZjP6VMReUVXpv3k3AoUKrkeLA",
          "cost_basis": -3230.25,
          "institution_price": 1.99,
          "institution_price_as_of": "2025-07-03",
          "institution_price_datetime": null,
          "institution_value": 29.85,
          "iso_currency_code": "USD",
          "quantity": 15,
          "security_id": "QPO8Jo8vdDHpwKJgmaePSYZvqRv3XPsbg3894",
          "unofficial_currency_code": null,
          "vested_quantity": null,
          "vested_value": null,
          "institution_name": "Merrill",
          "institution_id": "ins_115610"
        },
        {
          "account_id": "9rggQzXgqgSMZjP6VMReUVXpv3k3AoUKrkeLA",
          "cost_basis": -633.5,
          "institution_price": 3.01,
          "institution_price_as_of": "2025-07-03",
          "institution_price_datetime": null,
          "institution_value": 30.099999999999998,
          "iso_currency_code": "USD",
          "quantity": 10,
          "security_id": "AyvPNVPQ75Sm35nLqR0jfOXJP6JdVphZe51wZ",
          "unofficial_currency_code": null,
          "vested_quantity": null,
          "vested_value": null,
          "institution_name": "Merrill",
          "institution_id": "ins_115610"
        },
        {
          "account_id": "9rggQzXgqgSMZjP6VMReUVXpv3k3AoUKrkeLA",
          "cost_basis": -3186.75,
          "institution_price": 6.38,
          "institution_price_as_of": "2025-07-03",
          "institution_price_datetime": null,
          "institution_value": 31.9,
          "iso_currency_code": "USD",
          "quantity": 5,
          "security_id": "pJPM4LMBNQFwyL3aYV8qf8ZPB4P5yAfQNXmnN",
          "unofficial_currency_code": null,
          "vested_quantity": null,
          "vested_value": null,
          "institution_name": "Merrill",
          "institution_id": "ins_115610"
        },
        {
          "account_id": "9rggQzXgqgSMZjP6VMReUVXpv3k3AoUKrkeLA",
          "cost_basis": -653.5,
          "institution_price": 3.53,
          "institution_price_as_of": "2025-07-03",
          "institution_price_datetime": null,
          "institution_value": 35.3,
          "iso_currency_code": "USD",
          "quantity": 10,
          "security_id": "XARE85EJqKsLop0VpYrMFPABJMBv8NfPM9pDm",
          "unofficial_currency_code": null,
          "vested_quantity": null,
          "vested_value": null,
          "institution_name": "Merrill",
          "institution_id": "ins_115610"
        },
        {
          "account_id": "9rggQzXgqgSMZjP6VMReUVXpv3k3AoUKrkeLA",
          "cost_basis": -2453.95,
          "institution_price": 2.1,
          "institution_price_as_of": "2025-07-03",
          "institution_price_datetime": null,
          "institution_value": 35.7,
          "iso_currency_code": "USD",
          "quantity": 17,
          "security_id": "vLRMV3MvY1FqR16O19m3fJD5QN5rw9F7XdRzY",
          "unofficial_currency_code": null,
          "vested_quantity": null,
          "vested_value": null,
          "institution_name": "Merrill",
          "institution_id": "ins_115610"
        },
        {
          "account_id": "9rggQzXgqgSMZjP6VMReUVXpv3k3AoUKrkeLA",
          "cost_basis": -3425.4500000000003,
          "institution_price": 5.75,
          "institution_price_as_of": "2025-07-03",
          "institution_price_datetime": null,
          "institution_value": 40.25,
          "iso_currency_code": "USD",
          "quantity": 7,
          "security_id": "Yv3EpQE8BkIDRAYqxANMSm46e56O7MHpN4EgE",
          "unofficial_currency_code": null,
          "vested_quantity": null,
          "vested_value": null,
          "institution_name": "Merrill",
          "institution_id": "ins_115610"
        },
        {
          "account_id": "9rggQzXgqgSMZjP6VMReUVXpv3k3AoUKrkeLA",
          "cost_basis": -1507,
          "institution_price": 2.15,
          "institution_price_as_of": "2025-07-03",
          "institution_price_datetime": null,
          "institution_value": 43,
          "iso_currency_code": "USD",
          "quantity": 20,
          "security_id": "QPO8Jo8vdDHpw1MrZOLMIYZvqRv3XPsbgBVAX",
          "unofficial_currency_code": null,
          "vested_quantity": null,
          "vested_value": null,
          "institution_name": "Merrill",
          "institution_id": "ins_115610"
        },
        {
          "account_id": "9rggQzXgqgSMZjP6VMReUVXpv3k3AoUKrkeLA",
          "cost_basis": -1367,
          "institution_price": 4.04,
          "institution_price_as_of": "2025-07-03",
          "institution_price_datetime": null,
          "institution_value": 80.8,
          "iso_currency_code": "USD",
          "quantity": 20,
          "security_id": "wD7MdyM0NPfnA1dzoPwLf4em3wm5jDCeypVn9",
          "unofficial_currency_code": null,
          "vested_quantity": null,
          "vested_value": null,
          "institution_name": "Merrill",
          "institution_id": "ins_115610"
        },
        {
          "account_id": "9rggQzXgqgSMZjP6VMReUVXpv3k3AoUKrkeLA",
          "cost_basis": null,
          "institution_price": 46.56,
          "institution_price_as_of": "2025-07-03",
          "institution_price_datetime": null,
          "institution_value": 651.84,
          "iso_currency_code": "USD",
          "quantity": 14,
          "security_id": "NLqaJoaK5wFr6d4JxLarfnQpgJpNk6tKvJPOV",
          "unofficial_currency_code": null,
          "vested_quantity": null,
          "vested_value": null,
          "institution_name": "Merrill",
          "institution_id": "ins_115610"
        },
        {
          "account_id": "9rggQzXgqgSMZjP6VMReUVXpv3k3AoUKrkeLA",
          "cost_basis": null,
          "institution_price": 12.17,
          "institution_price_as_of": "2025-07-03",
          "institution_price_datetime": null,
          "institution_value": 25812.57,
          "iso_currency_code": "USD",
          "quantity": 2121,
          "security_id": "moPE4dE1yMHJXRvqvedVUvbZ1LZ7NVHdEykAJ",
          "unofficial_currency_code": null,
          "vested_quantity": null,
          "vested_value": null,
          "institution_name": "Merrill",
          "institution_id": "ins_115610"
        },
        {
          "account_id": "9rggQzXgqgSMZjP6VMReUVXpv3k3AoUKrkeLA",
          "cost_basis": 25610.000000000004,
          "institution_price": 308.55,
          "institution_price_as_of": "2025-07-03",
          "institution_price_datetime": null,
          "institution_value": 30855,
          "iso_currency_code": "USD",
          "quantity": 100,
          "security_id": "Z09ER5EZdAHRNkZBJXzYh8kyOLyDngfQPpE5m",
          "unofficial_currency_code": null,
          "vested_quantity": null,
          "vested_value": null,
          "institution_name": "Merrill",
          "institution_id": "ins_115610"
        },
        {
          "account_id": "9rggQzXgqgSMZjP6VMReUVXpv3k3AoUKrkeLA",
          "cost_basis": 43632,
          "institution_price": 17.66,
          "institution_price_as_of": "2025-07-03",
          "institution_price_datetime": null,
          "institution_value": 47682,
          "iso_currency_code": "USD",
          "quantity": 2700,
          "security_id": "M654JE4yQdCA0rvRRVXAIZJ3Lo34kKHQgDe4k",
          "unofficial_currency_code": null,
          "vested_quantity": null,
          "vested_value": null,
          "institution_name": "Merrill",
          "institution_id": "ins_115610"
        },
        {
          "account_id": "9rggQzXgqgSMZjP6VMReUVXpv3k3AoUKrkeLA",
          "cost_basis": 49808,
          "institution_price": 47.98,
          "institution_price_as_of": "2025-07-03",
          "institution_price_datetime": null,
          "institution_value": 52778,
          "iso_currency_code": "USD",
          "quantity": 1100,
          "security_id": "BK6qVpqnZouyYz7krLXrtXgvqovmnLC9eP3b4",
          "unofficial_currency_code": null,
          "vested_quantity": null,
          "vested_value": null,
          "institution_name": "Merrill",
          "institution_id": "ins_115610"
        },
        {
          "account_id": "9rggQzXgqgSMZjP6VMReUVXpv3k3AoUKrkeLA",
          "cost_basis": 47680,
          "institution_price": 18.57,
          "institution_price_as_of": "2025-07-03",
          "institution_price_datetime": null,
          "institution_value": 74280,
          "iso_currency_code": "USD",
          "quantity": 4000,
          "security_id": "Lw1rJor3kQs9OgepZ5zQtbry9EyDxKU05131p",
          "unofficial_currency_code": null,
          "vested_quantity": null,
          "vested_value": null,
          "institution_name": "Merrill",
          "institution_id": "ins_115610"
        },
        {
          "account_id": "9rggQzXgqgSMZjP6VMReUVXpv3k3AoUKrkeLA",
          "cost_basis": 53506.00000000001,
          "institution_price": 26.43,
          "institution_price_as_of": "2025-07-03",
          "institution_price_datetime": null,
          "institution_value": 81933,
          "iso_currency_code": "USD",
          "quantity": 3100,
          "security_id": "M654JE4yQdCA0YeD66oAIZJ3Lo34kKHQg9MXv",
          "unofficial_currency_code": null,
          "vested_quantity": null,
          "vested_value": null,
          "institution_name": "Merrill",
          "institution_id": "ins_115610"
        },
        {
          "account_id": "9rggQzXgqgSMZjP6VMReUVXpv3k3AoUKrkeLA",
          "cost_basis": 108756,
          "institution_price": 13.07,
          "institution_price_as_of": "2025-07-03",
          "institution_price_datetime": null,
          "institution_value": 99332,
          "iso_currency_code": "USD",
          "quantity": 7600,
          "security_id": "wD7MdyM0NPfnPJp5LD6gt4em3wm5jDCeLBXmV",
          "unofficial_currency_code": null,
          "vested_quantity": null,
          "vested_value": null,
          "institution_name": "Merrill",
          "institution_id": "ins_115610"
        },
        {
          "account_id": "9rggQzXgqgSMZjP6VMReUVXpv3k3AoUKrkeLA",
          "cost_basis": 72225,
          "institution_price": 130.98,
          "institution_price_as_of": "2025-07-03",
          "institution_price_datetime": null,
          "institution_value": 117881.99999999999,
          "iso_currency_code": "USD",
          "quantity": 900,
          "security_id": "JmN0JX0q5EcaQDbnX4E8tYzMgoMr6psg36zQv",
          "unofficial_currency_code": null,
          "vested_quantity": null,
          "vested_value": null,
          "institution_name": "Merrill",
          "institution_id": "ins_115610"
        }
      ],
      "accounts": [
        {
          "account_id": "9rggQzXgqgSMZjP6VMReUVXpv3k3AoUKrkeLA",
          "balances": {
            "available": 0,
            "current": 324395.16,
            "iso_currency_code": "USD",
            "limit": null,
            "unofficial_currency_code": null
          },
          "mask": "4196",
          "name": "CMA-Edge",
          "official_name": "CMA-Edge",
          "subtype": "cash management",
          "type": "depository",
          "institution_name": "Merrill",
          "institution_id": "ins_115610"
        },
        {
          "account_id": "VjaaRvpa8acogEkLmoX1CpvRVm9mbOfLaX1de",
          "balances": {
            "available": 0.03,
            "current": 6.03,
            "iso_currency_code": "USD",
            "limit": null,
            "unofficial_currency_code": null
          },
          "mask": "5630",
          "name": "INVESTMENT",
          "official_name": "CMA",
          "subtype": "cash management",
          "type": "depository",
          "institution_name": "Merrill",
          "institution_id": "ins_115610"
        }
      ],
      "securities": [
        {
          "close_price": null,
          "close_price_as_of": null,
          "cusip": null,
          "fixed_income": null,
          "industry": null,
          "institution_id": "ins_115610",
          "institution_security_id": null,
          "is_cash_equivalent": false,
          "isin": null,
          "iso_currency_code": "USD",
          "market_identifier_code": null,
          "name": "Put Nail 00050",
          "option_contract": null,
          "proxy_security_id": null,
          "sector": null,
          "security_id": "1vAj1Eja5BIRmXqJAv6NFBJ0q30AYZfq0O6Q8",
          "sedol": null,
          "ticker_symbol": "NAIL.S1825D500000",
          "type": "other",
          "unofficial_currency_code": null,
          "update_datetime": null,
          "institution_name": "Merrill"
        },
        {
          "close_price": 11.475,
          "close_price_as_of": "2025-07-03",
          "cusip": null,
          "fixed_income": null,
          "industry": "Packaged Software",
          "institution_id": "ins_115610",
          "institution_security_id": null,
          "is_cash_equivalent": false,
          "isin": null,
          "iso_currency_code": "USD",
          "market_identifier_code": "OOTC",
          "name": "Parrot",
          "option_contract": null,
          "proxy_security_id": null,
          "sector": "Technology Services",
          "security_id": "1vAj1Eja5BIn46g1KvjZsBJ0q30AYZf1r86Xk",
          "sedol": null,
          "ticker_symbol": "PAOTF",
          "type": "equity",
          "unofficial_currency_code": null,
          "update_datetime": null,
          "institution_name": "Merrill"
        },
        {
          "close_price": 50.12,
          "close_price_as_of": "2025-03-26",
          "cusip": null,
          "fixed_income": null,
          "industry": "Investment Trusts or Mutual Funds",
          "institution_id": "ins_115610",
          "institution_security_id": null,
          "is_cash_equivalent": false,
          "isin": null,
          "iso_currency_code": "USD",
          "market_identifier_code": "XNYS",
          "name": "GDL Fund - FXDVR PRF REDEEM 26/03/2025 USD 50 - Ser C",
          "option_contract": null,
          "proxy_security_id": null,
          "sector": "Miscellaneous",
          "security_id": "4r0aBVa85Kt3B14LJgEot5Pwzbwqopt0zQ13b",
          "sedol": "BF4J405",
          "ticker_symbol": "GDL/PR/C",
          "type": "equity",
          "unofficial_currency_code": null,
          "update_datetime": null,
          "institution_name": "Merrill"
        },
        {
          "close_price": null,
          "close_price_as_of": null,
          "cusip": null,
          "fixed_income": null,
          "industry": null,
          "institution_id": "ins_115610",
          "institution_security_id": null,
          "is_cash_equivalent": false,
          "isin": null,
          "iso_currency_code": "USD",
          "market_identifier_code": null,
          "name": "Call Rivn 00014",
          "option_contract": null,
          "proxy_security_id": null,
          "sector": null,
          "security_id": "7dD8KV8owvUX4XDnJVyeHLPy8Kyr9dFzwx7ep",
          "sedol": null,
          "ticker_symbol": "RIVN.E0925D140000",
          "type": "other",
          "unofficial_currency_code": null,
          "update_datetime": null,
          "institution_name": "Merrill"
        },
        {
          "close_price": null,
          "close_price_as_of": null,
          "cusip": null,
          "fixed_income": null,
          "industry": null,
          "institution_id": "ins_115610",
          "institution_security_id": null,
          "is_cash_equivalent": false,
          "isin": null,
          "iso_currency_code": "USD",
          "market_identifier_code": null,
          "name": "Call Unh 00320",
          "option_contract": null,
          "proxy_security_id": null,
          "sector": null,
          "security_id": "96d5AO5gLjCoqaeEex91UB1YdrYymNfrVZwxA",
          "sedol": null,
          "ticker_symbol": "UNH.C2026C320000",
          "type": "other",
          "unofficial_currency_code": null,
          "update_datetime": null,
          "institution_name": "Merrill"
        },
        {
          "close_price": null,
          "close_price_as_of": null,
          "cusip": null,
          "fixed_income": null,
          "industry": null,
          "institution_id": "ins_115610",
          "institution_security_id": null,
          "is_cash_equivalent": false,
          "isin": null,
          "iso_currency_code": "USD",
          "market_identifier_code": null,
          "name": "Call Hims 00048",
          "option_contract": null,
          "proxy_security_id": null,
          "sector": null,
          "security_id": "96d5AO5gLjCoqrDdx948IB1YdrYymNfrVLoRR",
          "sedol": null,
          "ticker_symbol": "HIMS.H0825D480000",
          "type": "other",
          "unofficial_currency_code": null,
          "update_datetime": null,
          "institution_name": "Merrill"
        },
        {
          "close_price": null,
          "close_price_as_of": null,
          "cusip": null,
          "fixed_income": null,
          "industry": null,
          "institution_id": "ins_115610",
          "institution_security_id": null,
          "is_cash_equivalent": false,
          "isin": null,
          "iso_currency_code": "USD",
          "market_identifier_code": null,
          "name": "SOFI 01/05/00 5.00 Call",
          "option_contract": {
            "contract_type": "call",
            "expiration_date": "2000-01-05",
            "strike_price": 5,
            "underlying_security_ticker": "SOFI"
          },
          "proxy_security_id": null,
          "sector": null,
          "security_id": "AyvPNVPQ75Sm35nLqR0jfOXJP6JdVphZe51wZ",
          "sedol": null,
          "ticker_symbol": "SOFI000105C00005000",
          "type": "derivative",
          "unofficial_currency_code": null,
          "update_datetime": null,
          "institution_name": "Merrill"
        },
        {
          "close_price": 47.98,
          "close_price_as_of": "2025-07-03",
          "cusip": null,
          "fixed_income": null,
          "industry": "Medical or Nursing Services",
          "institution_id": "ins_115610",
          "institution_security_id": null,
          "is_cash_equivalent": false,
          "isin": null,
          "iso_currency_code": "USD",
          "market_identifier_code": "XNYS",
          "name": "Hims & Hers Health Inc - Ordinary Shares - Class A",
          "option_contract": null,
          "proxy_security_id": null,
          "sector": "Health Services",
          "security_id": "BK6qVpqnZouyYz7krLXrtXgvqovmnLC9eP3b4",
          "sedol": null,
          "ticker_symbol": "HIMS",
          "type": "equity",
          "unofficial_currency_code": null,
          "update_datetime": null,
          "institution_name": "Merrill"
        },
        {
          "close_price": null,
          "close_price_as_of": null,
          "cusip": null,
          "fixed_income": null,
          "industry": null,
          "institution_id": "ins_115610",
          "institution_security_id": null,
          "is_cash_equivalent": true,
          "isin": null,
          "iso_currency_code": "USD",
          "market_identifier_code": null,
          "name": "Ml Bank Deposit Program",
          "option_contract": null,
          "proxy_security_id": null,
          "sector": null,
          "security_id": "EvByboy6Z7I4zm1p1Ya1TQ5R4YRjPMfZErRde",
          "sedol": null,
          "ticker_symbol": null,
          "type": "cash",
          "unofficial_currency_code": null,
          "update_datetime": null,
          "institution_name": "Merrill"
        },
        {
          "close_price": 97.99,
          "close_price_as_of": "2021-01-15",
          "cusip": null,
          "fixed_income": null,
          "industry": null,
          "institution_id": "ins_115610",
          "institution_security_id": null,
          "is_cash_equivalent": false,
          "isin": null,
          "iso_currency_code": "USD",
          "market_identifier_code": "XNYS",
          "name": "Sempra Energy - 6% PRF CONVERT 15/01/2021 USD 100 - Prf A",
          "option_contract": null,
          "proxy_security_id": null,
          "sector": null,
          "security_id": "EvByboy6Z7IdXMEM8rbgTQ5R4YRjPMfwqr9yR",
          "sedol": "BFMYYL3",
          "ticker_symbol": "SRE/PR/A",
          "type": "equity",
          "unofficial_currency_code": null,
          "update_datetime": null,
          "institution_name": "Merrill"
        },
        {
          "close_price": null,
          "close_price_as_of": null,
          "cusip": null,
          "fixed_income": null,
          "industry": null,
          "institution_id": "ins_115610",
          "institution_security_id": null,
          "is_cash_equivalent": false,
          "isin": null,
          "iso_currency_code": "USD",
          "market_identifier_code": null,
          "name": "Call Celh 00035",
          "option_contract": null,
          "proxy_security_id": null,
          "sector": null,
          "security_id": "JmN0JX0q5EcJzZakgAaXHYzMgoMr6psQ6ZPKo",
          "sedol": null,
          "ticker_symbol": "CELH.G0325D350000",
          "type": "other",
          "unofficial_currency_code": null,
          "update_datetime": null,
          "institution_name": "Merrill"
        },
        {
          "close_price": 130.98,
          "close_price_as_of": "2025-07-03",
          "cusip": null,
          "fixed_income": null,
          "industry": "Household or Personal Care",
          "institution_id": "ins_115610",
          "institution_security_id": null,
          "is_cash_equivalent": false,
          "isin": null,
          "iso_currency_code": "USD",
          "market_identifier_code": "XNYS",
          "name": "e.l.f. Beauty Inc",
          "option_contract": null,
          "proxy_security_id": null,
          "sector": "Consumer Non-Durables",
          "security_id": "JmN0JX0q5EcaQDbnX4E8tYzMgoMr6psg36zQv",
          "sedol": null,
          "ticker_symbol": "ELF",
          "type": "equity",
          "unofficial_currency_code": null,
          "update_datetime": null,
          "institution_name": "Merrill"
        },
        {
          "close_price": 18.57,
          "close_price_as_of": "2025-07-03",
          "cusip": null,
          "fixed_income": null,
          "industry": "Finance or Rental or Leasing",
          "institution_id": "ins_115610",
          "institution_security_id": null,
          "is_cash_equivalent": false,
          "isin": null,
          "iso_currency_code": "USD",
          "market_identifier_code": "XNAS",
          "name": "SoFi Technologies Inc",
          "option_contract": null,
          "proxy_security_id": null,
          "sector": "Finance",
          "security_id": "Lw1rJor3kQs9OgepZ5zQtbry9EyDxKU05131p",
          "sedol": null,
          "ticker_symbol": "SOFI",
          "type": "equity",
          "unofficial_currency_code": null,
          "update_datetime": null,
          "institution_name": "Merrill"
        },
        {
          "close_price": 26.43,
          "close_price_as_of": "2025-07-03",
          "cusip": null,
          "fixed_income": null,
          "industry": "Investment Trusts or Mutual Funds",
          "institution_id": "ins_115610",
          "institution_security_id": null,
          "is_cash_equivalent": false,
          "isin": null,
          "iso_currency_code": "USD",
          "market_identifier_code": "ARCX",
          "name": "Direxion Shares ETF Trust - Direxion Daily Semiconductor Bull 3X Shares",
          "option_contract": null,
          "proxy_security_id": null,
          "sector": "Miscellaneous",
          "security_id": "M654JE4yQdCA0YeD66oAIZJ3Lo34kKHQg9MXv",
          "sedol": "B63HHG4",
          "ticker_symbol": "SOXL",
          "type": "etf",
          "unofficial_currency_code": null,
          "update_datetime": null,
          "institution_name": "Merrill"
        },
        {
          "close_price": 17.66,
          "close_price_as_of": "2025-07-03",
          "cusip": null,
          "fixed_income": null,
          "industry": "Data Processing Services",
          "institution_id": "ins_115610",
          "institution_security_id": null,
          "is_cash_equivalent": false,
          "isin": null,
          "iso_currency_code": "USD",
          "market_identifier_code": "XNAS",
          "name": "MARA Holdings Inc.",
          "option_contract": null,
          "proxy_security_id": null,
          "sector": "Technology Services",
          "security_id": "M654JE4yQdCA0rvRRVXAIZJ3Lo34kKHQgDe4k",
          "sedol": null,
          "ticker_symbol": "MARA",
          "type": "equity",
          "unofficial_currency_code": null,
          "update_datetime": null,
          "institution_name": "Merrill"
        },
        {
          "close_price": 46.56,
          "close_price_as_of": "2025-07-03",
          "cusip": null,
          "fixed_income": null,
          "industry": "Non-Alcoholic Beverages",
          "institution_id": "ins_115610",
          "institution_security_id": null,
          "is_cash_equivalent": false,
          "isin": null,
          "iso_currency_code": "USD",
          "market_identifier_code": "XNAS",
          "name": "Celsius Holdings Inc",
          "option_contract": null,
          "proxy_security_id": null,
          "sector": "Consumer Non-Durables",
          "security_id": "NLqaJoaK5wFr6d4JxLarfnQpgJpNk6tKvJPOV",
          "sedol": null,
          "ticker_symbol": "CELH",
          "type": "equity",
          "unofficial_currency_code": null,
          "update_datetime": null,
          "institution_name": "Merrill"
        },
        {
          "close_price": null,
          "close_price_as_of": null,
          "cusip": null,
          "fixed_income": null,
          "industry": null,
          "institution_id": "ins_115610",
          "institution_security_id": null,
          "is_cash_equivalent": false,
          "isin": null,
          "iso_currency_code": "USD",
          "market_identifier_code": null,
          "name": "Call Riot 00010",
          "option_contract": null,
          "proxy_security_id": null,
          "sector": null,
          "security_id": "QPO8Jo8vdDHpw1MrZOLMIYZvqRv3XPsbgBVAX",
          "sedol": null,
          "ticker_symbol": "RIOT.G1125D100000",
          "type": "other",
          "unofficial_currency_code": null,
          "update_datetime": null,
          "institution_name": "Merrill"
        },
        {
          "close_price": null,
          "close_price_as_of": null,
          "cusip": null,
          "fixed_income": null,
          "industry": null,
          "institution_id": "ins_115610",
          "institution_security_id": null,
          "is_cash_equivalent": false,
          "isin": null,
          "iso_currency_code": "USD",
          "market_identifier_code": null,
          "name": "Call Soxl 00028",
          "option_contract": null,
          "proxy_security_id": null,
          "sector": null,
          "security_id": "QPO8Jo8vdDHpwKJgmaePSYZvqRv3XPsbg3894",
          "sedol": null,
          "ticker_symbol": "SOXL.G0325D280000",
          "type": "other",
          "unofficial_currency_code": null,
          "update_datetime": null,
          "institution_name": "Merrill"
        },
        {
          "close_price": null,
          "close_price_as_of": null,
          "cusip": null,
          "fixed_income": null,
          "industry": null,
          "institution_id": "ins_115610",
          "institution_security_id": null,
          "is_cash_equivalent": false,
          "isin": null,
          "iso_currency_code": "USD",
          "market_identifier_code": null,
          "name": "Call Riot 00008.5",
          "option_contract": null,
          "proxy_security_id": null,
          "sector": null,
          "security_id": "RqmZJoZ0w1coO7PmydbwIMzaB8agQZfdbEaXO",
          "sedol": null,
          "ticker_symbol": "RIOT.G0325E850000",
          "type": "other",
          "unofficial_currency_code": null,
          "update_datetime": null,
          "institution_name": "Merrill"
        },
        {
          "close_price": null,
          "close_price_as_of": null,
          "cusip": null,
          "fixed_income": null,
          "industry": null,
          "institution_id": "ins_115610",
          "institution_security_id": null,
          "is_cash_equivalent": false,
          "isin": null,
          "iso_currency_code": "USD",
          "market_identifier_code": null,
          "name": "Call Rivn 00015",
          "option_contract": null,
          "proxy_security_id": null,
          "sector": null,
          "security_id": "XARE85EJqKsLoVnPjM1McPABJMBv8NfPMDKkx",
          "sedol": null,
          "ticker_symbol": "RIVN.G2525D150000",
          "type": "other",
          "unofficial_currency_code": null,
          "update_datetime": null,
          "institution_name": "Merrill"
        },
        {
          "close_price": null,
          "close_price_as_of": null,
          "cusip": null,
          "fixed_income": null,
          "industry": null,
          "institution_id": "ins_115610",
          "institution_security_id": null,
          "is_cash_equivalent": false,
          "isin": null,
          "iso_currency_code": "USD",
          "market_identifier_code": null,
          "name": "Call Sofi 00015",
          "option_contract": null,
          "proxy_security_id": "1vAj1Eja5BIn46g1KvjZsBJ0q30AYZf1r86Xk",
          "sector": null,
          "security_id": "XARE85EJqKsLop0VpYrMFPABJMBv8NfPM9pDm",
          "sedol": null,
          "ticker_symbol": "SOFI.D1725D150000",
          "type": "derivative",
          "unofficial_currency_code": null,
          "update_datetime": null,
          "institution_name": "Merrill"
        },
        {
          "close_price": null,
          "close_price_as_of": null,
          "cusip": null,
          "fixed_income": null,
          "industry": null,
          "institution_id": "ins_115610",
          "institution_security_id": null,
          "is_cash_equivalent": false,
          "isin": null,
          "iso_currency_code": "USD",
          "market_identifier_code": null,
          "name": "RIVN 01/04/00 5.00 Call",
          "option_contract": {
            "contract_type": "call",
            "expiration_date": "2000-01-04",
            "strike_price": 5,
            "underlying_security_ticker": "RIVN"
          },
          "proxy_security_id": "EvByboy6Z7IdXMEM8rbgTQ5R4YRjPMfwqr9yR",
          "sector": null,
          "security_id": "XARE85EJqKsLrXzjxokRiPABJMBv8NfP8JQAM",
          "sedol": null,
          "ticker_symbol": "RIVN000104C00005000",
          "type": "derivative",
          "unofficial_currency_code": null,
          "update_datetime": null,
          "institution_name": "Merrill"
        },
        {
          "close_price": null,
          "close_price_as_of": null,
          "cusip": null,
          "fixed_income": null,
          "industry": null,
          "institution_id": "ins_115610",
          "institution_security_id": null,
          "is_cash_equivalent": false,
          "isin": null,
          "iso_currency_code": "USD",
          "market_identifier_code": null,
          "name": "Call Hims 00044",
          "option_contract": null,
          "proxy_security_id": null,
          "sector": null,
          "security_id": "Yv3EpQE8BkIDRAYqxANMSm46e56O7MHpN4EgE",
          "sedol": null,
          "ticker_symbol": "HIMS.G2525D440000",
          "type": "other",
          "unofficial_currency_code": null,
          "update_datetime": null,
          "institution_name": "Merrill"
        },
        {
          "close_price": 308.55,
          "close_price_as_of": "2025-07-03",
          "cusip": null,
          "fixed_income": null,
          "industry": "Managed Health Care",
          "institution_id": "ins_115610",
          "institution_security_id": null,
          "is_cash_equivalent": false,
          "isin": null,
          "iso_currency_code": "USD",
          "market_identifier_code": "XNYS",
          "name": "Unitedhealth Group Inc",
          "option_contract": null,
          "proxy_security_id": null,
          "sector": "Health Services",
          "security_id": "Z09ER5EZdAHRNkZBJXzYh8kyOLyDngfQPpE5m",
          "sedol": "2917766",
          "ticker_symbol": "UNH",
          "type": "equity",
          "unofficial_currency_code": null,
          "update_datetime": null,
          "institution_name": "Merrill"
        },
        {
          "close_price": null,
          "close_price_as_of": null,
          "cusip": null,
          "fixed_income": null,
          "industry": null,
          "institution_id": "ins_115610",
          "institution_security_id": null,
          "is_cash_equivalent": false,
          "isin": null,
          "iso_currency_code": "USD",
          "market_identifier_code": null,
          "name": "Put Riot 00010.5",
          "option_contract": null,
          "proxy_security_id": null,
          "sector": null,
          "security_id": "moPE4dE1yMH5xRJ8Z48YtvbZ1LZ7NVH4RwKaj",
          "sedol": null,
          "ticker_symbol": "RIOT.S1125D105000",
          "type": "other",
          "unofficial_currency_code": null,
          "update_datetime": null,
          "institution_name": "Merrill"
        },
        {
          "close_price": 12.17,
          "close_price_as_of": "2025-07-03",
          "cusip": null,
          "fixed_income": null,
          "industry": "Information Technology Services",
          "institution_id": "ins_115610",
          "institution_security_id": null,
          "is_cash_equivalent": false,
          "isin": null,
          "iso_currency_code": "USD",
          "market_identifier_code": "XNAS",
          "name": "Riot Platforms Inc",
          "option_contract": null,
          "proxy_security_id": null,
          "sector": "Technology Services",
          "security_id": "moPE4dE1yMHJXRvqvedVUvbZ1LZ7NVHdEykAJ",
          "sedol": "BD9F675",
          "ticker_symbol": "RIOT",
          "type": "equity",
          "unofficial_currency_code": null,
          "update_datetime": null,
          "institution_name": "Merrill"
        },
        {
          "close_price": null,
          "close_price_as_of": null,
          "cusip": null,
          "fixed_income": null,
          "industry": null,
          "institution_id": "ins_115610",
          "institution_security_id": null,
          "is_cash_equivalent": false,
          "isin": null,
          "iso_currency_code": "USD",
          "market_identifier_code": null,
          "name": "MARA 01/06/00 5.00 Call",
          "option_contract": {
            "contract_type": "call",
            "expiration_date": "2000-01-06",
            "strike_price": 5,
            "underlying_security_ticker": "MARA"
          },
          "proxy_security_id": "4r0aBVa85Kt3B14LJgEot5Pwzbwqopt0zQ13b",
          "sector": null,
          "security_id": "pJPM4LMBNQFwPmy0jJePt8ZPB4P5yAfQ7D69w",
          "sedol": null,
          "ticker_symbol": "MARA000106C00005000",
          "type": "derivative",
          "unofficial_currency_code": null,
          "update_datetime": null,
          "institution_name": "Merrill"
        },
        {
          "close_price": null,
          "close_price_as_of": null,
          "cusip": null,
          "fixed_income": null,
          "industry": null,
          "institution_id": "ins_115610",
          "institution_security_id": null,
          "is_cash_equivalent": false,
          "isin": null,
          "iso_currency_code": "USD",
          "market_identifier_code": null,
          "name": "Put Nail 00058",
          "option_contract": null,
          "proxy_security_id": null,
          "sector": null,
          "security_id": "pJPM4LMBNQFwyL3aYV8qf8ZPB4P5yAfQNXmnN",
          "sedol": null,
          "ticker_symbol": "NAIL.T1525D580000",
          "type": "other",
          "unofficial_currency_code": null,
          "update_datetime": null,
          "institution_name": "Merrill"
        },
        {
          "close_price": null,
          "close_price_as_of": null,
          "cusip": null,
          "fixed_income": null,
          "industry": null,
          "institution_id": "ins_115610",
          "institution_security_id": null,
          "is_cash_equivalent": false,
          "isin": null,
          "iso_currency_code": "USD",
          "market_identifier_code": null,
          "name": "Put Mara 00017",
          "option_contract": null,
          "proxy_security_id": null,
          "sector": null,
          "security_id": "rJ6M41My0wFLwNOZykgDt3exyOxkp7fAY6n75",
          "sedol": null,
          "ticker_symbol": "MARA.S2525D170000",
          "type": "other",
          "unofficial_currency_code": null,
          "update_datetime": null,
          "institution_name": "Merrill"
        },
        {
          "close_price": null,
          "close_price_as_of": null,
          "cusip": null,
          "fixed_income": null,
          "industry": null,
          "institution_id": "ins_115610",
          "institution_security_id": null,
          "is_cash_equivalent": false,
          "isin": null,
          "iso_currency_code": "USD",
          "market_identifier_code": null,
          "name": "Call Mara 00017",
          "option_contract": null,
          "proxy_security_id": null,
          "sector": null,
          "security_id": "vLRMV3MvY1FqR16O19m3fJD5QN5rw9F7XdRzY",
          "sedol": null,
          "ticker_symbol": "MARA.E1625D170000",
          "type": "other",
          "unofficial_currency_code": null,
          "update_datetime": null,
          "institution_name": "Merrill"
        },
        {
          "close_price": null,
          "close_price_as_of": null,
          "cusip": null,
          "fixed_income": null,
          "industry": null,
          "institution_id": "ins_115610",
          "institution_security_id": null,
          "is_cash_equivalent": false,
          "isin": null,
          "iso_currency_code": "USD",
          "market_identifier_code": null,
          "name": "SOFI 01/04/00 5.00 Call",
          "option_contract": {
            "contract_type": "call",
            "expiration_date": "2000-01-04",
            "strike_price": 5,
            "underlying_security_ticker": "SOFI"
          },
          "proxy_security_id": null,
          "sector": null,
          "security_id": "wD7MdyM0NPfnA1dzoPwLf4em3wm5jDCeypVn9",
          "sedol": null,
          "ticker_symbol": "SOFI000104C00005000",
          "type": "derivative",
          "unofficial_currency_code": null,
          "update_datetime": null,
          "institution_name": "Merrill"
        },
        {
          "close_price": 13.07,
          "close_price_as_of": "2025-07-03",
          "cusip": null,
          "fixed_income": null,
          "industry": "Motor Vehicles",
          "institution_id": "ins_115610",
          "institution_security_id": null,
          "is_cash_equivalent": false,
          "isin": null,
          "iso_currency_code": "USD",
          "market_identifier_code": "XNAS",
          "name": "Rivian Automotive Inc - Ordinary Shares - Class A",
          "option_contract": null,
          "proxy_security_id": null,
          "sector": "Consumer Durables",
          "security_id": "wD7MdyM0NPfnPJp5LD6gt4em3wm5jDCeLBXmV",
          "sedol": null,
          "ticker_symbol": "RIVN",
          "type": "equity",
          "unofficial_currency_code": null,
          "update_datetime": null,
          "institution_name": "Merrill"
        },
        {
          "close_price": null,
          "close_price_as_of": null,
          "cusip": null,
          "fixed_income": null,
          "industry": null,
          "institution_id": "ins_115610",
          "institution_security_id": null,
          "is_cash_equivalent": false,
          "isin": null,
          "iso_currency_code": "USD",
          "market_identifier_code": null,
          "name": "SOFI 01/06/00 5.00 Put",
          "option_contract": {
            "contract_type": "put",
            "expiration_date": "2000-01-06",
            "strike_price": 5,
            "underlying_security_ticker": "SOFI"
          },
          "proxy_security_id": null,
          "sector": null,
          "security_id": "yPmM6kMrNBHBkQZY58XkIXxEeYEb0KCDpaPgQ",
          "sedol": null,
          "ticker_symbol": "SOFI000106P00005000",
          "type": "derivative",
          "unofficial_currency_code": null,
          "update_datetime": null,
          "institution_name": "Merrill"
        }
      ]
    }
  }
}